ecco_v4_py/__init__.py
ecco_v4_py/calc_meridional_trsp.py
ecco_v4_py/calc_meridional_trsp_isopycnals.py
ecco_v4_py/calc_section_trsp.py
ecco_v4_py/calc_stf.py
ecco_v4_py/ecco_access.py
ecco_v4_py/ecco_utils.py
ecco_v4_py/get_basin.py
ecco_v4_py/get_section_masks.py
ecco_v4_py/llc_array_conversion.py
ecco_v4_py/netcdf_product_generation.py
ecco_v4_py/plot_utils.py
ecco_v4_py/read_bin_gen.py
ecco_v4_py/read_bin_llc.py
ecco_v4_py/resample_to_latlon.py
ecco_v4_py/scalar_calc.py
ecco_v4_py/tile_io.py
ecco_v4_py/tile_plot.py
ecco_v4_py/tile_plot_proj.py
ecco_v4_py/vector_calc.py
ecco_v4_py/.ipynb_checkpoints/ecco_access-checkpoint.py
ecco_v4_py/.ipynb_checkpoints/ecco_s3_retrieve-checkpoint.py
ecco_v4_py/test/__init__.py
ecco_v4_py/test/test_common.py
ecco_v4_py/test/test_ecco_utils.py
ecco_v4_py/test/test_generate_ecco_netcdf_product.py
ecco_v4_py/test/test_get_basin.py
ecco_v4_py/test/test_llc_array_conversion.py
ecco_v4_py/test/test_meridional_trsp.py
ecco_v4_py/test/test_plot_utils.py
ecco_v4_py/test/test_proj_plot.py
ecco_v4_py/test/test_read_mds.py
ecco_v4_py/test/test_scalar_calc.py
ecco_v4_py/test/test_section_masks.py
ecco_v4_py/test/test_section_trsp.py
ecco_v4_py/test/test_stf.py
ecco_v4_py/test/test_tile_plot.py
ecco_v4_py/test/test_vector_calc.py
ecco_v4_py-1.8.0.data/data/binary_data/basins.data
ecco_v4_py-1.8.0.data/data/binary_data/basins.meta
ecco_v4_py-1.8.0.dist-info/licenses/LICENSE.txt
ecco_v4_py-1.8.0.dist-info/METADATA
ecco_v4_py-1.8.0.dist-info/WHEEL
ecco_v4_py-1.8.0.dist-info/top_level.txt
ecco_v4_py-1.8.0.dist-info/RECORD
