Metadata-Version: 2.4
Name: ecco_v4_py
Version: 1.8.0
Summary: Estimating the Circulation and Climate of the Ocean (ECCO) Version 4 Python Package
Home-page: https://github.com/ECCO-GROUP/ECCOv4-py
Author: Ian Fenty, Ou Wang, Tim Smith, Andrew Delman, and others
Author-email: ian.fenty@jpl.nasa.gov, ecco-group@mit.edu
License: MIT
Keywords: ecco,climate,mitgcm,estimate,circulation,climate
Classifier: Development Status :: 5 - Production/Stable
Classifier: Intended Audience :: Science/Research
Classifier: Natural Language :: English
Classifier: Programming Language :: Python
Classifier: Programming Language :: Python :: 3.7
Classifier: Programming Language :: Python :: 3.8
Classifier: Programming Language :: Python :: 3.9
Classifier: Programming Language :: Python :: 3.10
Classifier: Programming Language :: Python :: 3.11
Classifier: Programming Language :: Python :: 3.12
Classifier: Programming Language :: Python :: 3.13
Classifier: Topic :: Scientific/Engineering :: Physics
Requires-Python: >=3.7
License-File: LICENSE.txt
Requires-Dist: numpy
Requires-Dist: future
Requires-Dist: bottleneck
Requires-Dist: cartopy
Requires-Dist: cmocean
Requires-Dist: dask[complete]
Requires-Dist: matplotlib
Requires-Dist: netCDF4
Requires-Dist: pandas
Requires-Dist: pyresample
Requires-Dist: python-dateutil
Requires-Dist: xarray
Requires-Dist: xmitgcm
Requires-Dist: xgcm>=0.5.0
Dynamic: author
Dynamic: author-email
Dynamic: classifier
Dynamic: description
Dynamic: description-content-type
Dynamic: home-page
Dynamic: keywords
Dynamic: license
Dynamic: license-file
Dynamic: requires-dist
Dynamic: requires-python
Dynamic: summary
